<?xml version="1.0" encoding="UTF-8"?>
<extension id="geocodingfield" status="released" xmlns="http://getsymphony.com/schemas/extension/1.0">
	<name>Field: Geocoding</name>
	<description>Populates fields with geocoding information using the combined values of other fields.</description>
	<repo type="github">https://github.com/twiro/geocodingfield/</repo>
	<url type="issues">https://github.com/twiro/geocodingfield/issues/</url>
	<url type="discuss">https://www.getsymphony.com/discuss/thread/46536/</url>
	<types>
		<type>Field Types</type>
	</types>
	<authors>
		<author>
			<name github="twiro" symphony="roman">Roman Klein</name>
			<website>https://github.com/twiro</website>
		</author>
	</authors>
	<releases>
		<release version="2.0.0.beta" date="2018-09-23" min="2.5" max="2.x.x">
			- PHP 7 Support
			- Symphony 2.7 compatibility
			- Add Google Maps API Key to configuration
			- Code cleanup
		</release>
		<release version="1.0.2" date="2013-09-17" min="2.3" max="2.6.x">
			- Updated field label to follow Symphony core field structure by using label element instead of p element.
		</release>
		<release version="1.0.1" date="2013-03-08" min="2.3">
			- Use Geocoding API (V3)
		</release>
		<release version="1.0" date="2012-05-12" min="2.3">
			- Symphony 2.3 compatibility
			- Show map of location in entry table and publish panel
			- Add distance to datasource XML output when the field is used as a filter
		</release>
		<release version="0.7" date="2011-02-01" min="2.2"/>
	</releases>
</extension>
